password_validation/__init__.py
password_validation/calculate.py
password_validation/character_pool.py
password_validation/exceptions.py
password_validation/funcs.py
password_validation/password.py
password_validation/policy.py
Password_Validation-0.1.1.dist-info/LICENSE.md
Password_Validation-0.1.1.dist-info/METADATA
Password_Validation-0.1.1.dist-info/WHEEL
Password_Validation-0.1.1.dist-info/top_level.txt
Password_Validation-0.1.1.dist-info/RECORD
