Metadata-Version: 2.1
Name: Password-Validation
Version: 0.1.1
Summary: A simple API to validate passwords according to basic guidelines
Home-page: https://github.com/jackwardell/PasswordValidation
Author: Jack Wardell
License: UNKNOWN
Platform: UNKNOWN
Classifier: Programming Language :: Python :: 3
Classifier: License :: OSI Approved :: MIT License
Classifier: Operating System :: OS Independent
Requires-Python: >=3.6
